napari_mass/DataModel.py
napari_mass/ExternalTspSolver.py
napari_mass/OmeSource.py
napari_mass/OmeZarrSource.py
napari_mass/ParamControl.py
napari_mass/PathControl.py
napari_mass/Point.py
napari_mass/QtViewerModelWrap.py
napari_mass/Section.py
napari_mass/Stitcher.py
napari_mass/TiffSource.py
napari_mass/TiffTileMetadata.py
napari_mass/TiffTileSource.py
napari_mass/__init__.py
napari_mass/_widget.py
napari_mass/debug.py
napari_mass/features.py
napari_mass/napari.yaml
napari_mass/parameters.py
napari_mass/point_matching.py
napari_mass/section_detection.py
napari_mass/util.py
napari_mass/_tests/__init__.py
napari_mass/_tests/test_widget.py
napari_mass/file/DataFile.py
napari_mass/file/FileDict.py
napari_mass/file/MagcFile.py
napari_mass/file/csv_file.py
napari_mass/file/resources.py
napari_mass/image/color_conversion.py
napari_mass/image/util.py
napari_mass/resources/template.massproject.yml
napari_mass/testing/datafile_conversion.py
napari_mass/testing/datafile_test.py
napari_mass/testing/image_test.py
napari_mass/testing/optical_flow_testing.py
napari_mass-0.6.7.dist-info/licenses/LICENSE.md
napari_mass-0.6.7.dist-info/METADATA
napari_mass-0.6.7.dist-info/WHEEL
napari_mass-0.6.7.dist-info/entry_points.txt
napari_mass-0.6.7.dist-info/top_level.txt
napari_mass-0.6.7.dist-info/RECORD
