Metadata-Version: 2.4
Name: napari-mass
Version: 0.6.7
Summary: Microscopy Array Section Setup napari plugin
Author: Joost de Folter
Author-email: folterj@gmail.com
Project-URL: Bug Tracker, https://github.com/FrancisCrickInstitute/napari-mass/issues
Project-URL: Documentation, https://github.com/FrancisCrickInstitute/napari-mass#README.md
Project-URL: Source Code, https://github.com/FrancisCrickInstitute/napari-mass
Project-URL: User Support, https://github.com/FrancisCrickInstitute/napari-mass/issues
Classifier: Development Status :: 2 - Pre-Alpha
Classifier: Framework :: napari
Classifier: Intended Audience :: Developers
Classifier: License :: OSI Approved :: GNU General Public License v3 (GPLv3)
Classifier: Operating System :: OS Independent
Classifier: Programming Language :: Python
Classifier: Programming Language :: Python :: 3
Classifier: Programming Language :: Python :: 3 :: Only
Classifier: Programming Language :: Python :: 3.10
Classifier: Programming Language :: Python :: 3.11
Classifier: Programming Language :: Python :: 3.12
Classifier: Topic :: Scientific/Engineering :: Image Processing
Requires-Python: >=3.10
License-File: LICENSE.md
Requires-Dist: numpy
Requires-Dist: napari-ome-zarr
Requires-Dist: dask
Requires-Dist: scikit-learn
Requires-Dist: scikit-image
Requires-Dist: opencv-contrib-python-headless
Requires-Dist: tifffile
Requires-Dist: matplotlib
Provides-Extra: testing
Requires-Dist: tox; extra == "testing"
Requires-Dist: pytest; extra == "testing"
Requires-Dist: pytest-cov; extra == "testing"
Requires-Dist: pytest-qt; extra == "testing"
Requires-Dist: napari; extra == "testing"
Requires-Dist: pyqt5; extra == "testing"
Dynamic: license-file
